exml/__init__.py
exml/py.typed
exml-0.3.0.1.dist-info/METADATA
exml-0.3.0.1.dist-info/WHEEL
exml-0.3.0.1.dist-info/RECORD
