Metadata-Version: 2.4
Name: exml
Version: 0.3.0.1
Summary: A tiny eDSL to generate HTML/SVG/XML-looking strings.
Author-email: IC Rainbow <aenor.realm@gmail.com>
Requires-Python: >=3.10
